kaitorch/__init__.py
kaitorch/activations.py
kaitorch/core.py
kaitorch/functional.py
kaitorch/graph.py
kaitorch/initializers.py
kaitorch/layers.py
kaitorch/losses.py
kaitorch/models.py
kaitorch/optimizers.py
kaitorch/utils.py
kaitorch-0.1.0.dist-info/LICENSE
kaitorch-0.1.0.dist-info/METADATA
kaitorch-0.1.0.dist-info/WHEEL
kaitorch-0.1.0.dist-info/top_level.txt
kaitorch-0.1.0.dist-info/RECORD
