Metadata-Version: 2.1
Name: kaitorch
Version: 0.1.0
Summary: A Keras-like neural network library with an autograd engine operating on a dynamically built DAG of scalar values
Home-page: https://github.com/kaihayden/kaitorch
Author: Kai Hayden
Author-email: kaihayden97@gmail.com
License: UNKNOWN
Platform: UNKNOWN
Classifier: Programming Language :: Python :: 3
Classifier: License :: OSI Approved :: MIT License
Classifier: Operating System :: OS Independent
Requires-Python: >=3.6
License-File: LICENSE
